train_lib/__init__.py
train_lib/clients/__init__.py
train_lib/clients/fhir/__init__.py
train_lib/clients/fhir/fhir_client.py
train_lib/clients/fhir/fhir_k_anonymity.py
train_lib/clients/fhir/fhir_query_builder.py
train_lib/clients/fhir/minimal_query.json
train_lib/clients/fhir/query.json
train_lib/docker_util/__init__.py
train_lib/docker_util/docker_ops.py
train_lib/docker_util/validate_master_image.py
train_lib/security/__init__.py
train_lib/security/constants.py
train_lib/security/encryption.py
train_lib/security/errors.py
train_lib/security/hashing.py
train_lib/security/homomorphic_addition.py
train_lib/security/key_manager.py
train_lib/security/primes.py
train_lib/security/protocol.py
train_lib/security/train_config.py
train_lib/tests/archive.tar
train_lib/tests/conftest.py
train_lib/tests/test_fhir_functionality.py
train_lib/tests/test_homomorphic_addition.py
train_lib/tests/test_key_manager.py
train_lib/tests/test_security_functions.py
train_lib/tests/test_security_protocol.py
train_lib/tests/test_validate_master_image.py
pht_train_container_library-2.0.6.dist-info/LICENSE.txt
pht_train_container_library-2.0.6.dist-info/METADATA
pht_train_container_library-2.0.6.dist-info/WHEEL
pht_train_container_library-2.0.6.dist-info/RECORD
