Metadata-Version: 2.1
Name: pht-train-container-library
Version: 2.0.6
Summary: Python library for handling containerized PHT trains
Author: Michael Graf
Author-email: michael.graf@uni-tuebingen.com
Requires-Python: >=3.8,<4.0
Classifier: Programming Language :: Python :: 3
Classifier: Programming Language :: Python :: 3.8
Classifier: Programming Language :: Python :: 3.9
Classifier: Programming Language :: Python :: 3.10
Classifier: Programming Language :: Python :: 3.11
Requires-Dist: cryptography
Requires-Dist: docker
Requires-Dist: fhir-kindling
Requires-Dist: loguru
Requires-Dist: pandas
Requires-Dist: pendulum
Requires-Dist: requests
Requires-Dist: requests_oauthlib
